palantir/__init__.py
palantir/_version.py
palantir/core/__init__.py
palantir/core/config.py
palantir/core/functions.py
palantir/core/rpc.py
palantir/core/types.py
palantir/core/util.py
palantir/datasets/__init__.py
palantir/datasets/client.py
palantir/datasets/core.py
palantir/datasets/errors.py
palantir/datasets/functions.py
palantir/datasets/rpc/__init__.py
palantir/datasets/rpc/catalog.py
palantir/datasets/rpc/data_proxy.py
palantir/datasets/rpc/path.py
palantir/datasets/rpc/schema.py
palantir/datasets/rpc/sql.py
palantir/datasets/rpc/util.py
palantir/datasets/schema.py
palantir/datasets/types.py
palantir/py.typed
palantir_sdk-0.12.0.dist-info/WHEEL
palantir_sdk-0.12.0.dist-info/METADATA
palantir_sdk-0.12.0.dist-info/LICENSE
palantir_sdk-0.12.0.dist-info/RECORD
