Metadata-Version: 2.1
Name: palantir-sdk
Version: 0.12.0
Summary: Palantir Python SDK
Home-page: https://github.com/palantir/palantir-python-sdk
License: Apache-2.0
Author: Andrew Higgins
Author-email: ahiggins@palantir.com
Requires-Python: >=3.8,<4.0
Classifier: License :: OSI Approved :: Apache Software License
Classifier: Programming Language :: Python :: 3
Classifier: Programming Language :: Python :: 3.8
Classifier: Programming Language :: Python :: 3.9
Classifier: Programming Language :: Python :: 3.10
Classifier: Programming Language :: Python :: 3.11
Requires-Dist: conjure-python-client (>=2.1.0,<3.0.0)
Requires-Dist: tomli (>=2.0.1,<3.0.0)
